{"trial_id": "0242", "hyperparameters": {"space": [{"class_name": "Choice", "config": {"name": "activation", "default": "relu", "conditions": [], "values": ["relu", "tanh", "sigmoid"], "ordered": false}}, {"class_name": "Int", "config": {"name": "first_units", "default": null, "conditions": [], "min_value": 1, "max_value": 200, "step": 2, "sampling": null}}, {"class_name": "Int", "config": {"name": "num_layers", "default": null, "conditions": [], "min_value": 1, "max_value": 6, "step": 1, "sampling": null}}, {"class_name": "Int", "config": {"name": "units_0", "default": null, "conditions": [], "min_value": 1, "max_value": 200, "step": 2, "sampling": null}}, {"class_name": "Int", "config": {"name": "units_1", "default": null, "conditions": [], "min_value": 1, "max_value": 200, "step": 2, "sampling": null}}, {"class_name": "Int", "config": {"name": "units_2", "default": null, "conditions": [], "min_value": 1, "max_value": 200, "step": 2, "sampling": null}}, {"class_name": "Int", "config": {"name": "units_3", "default": null, "conditions": [], "min_value": 1, "max_value": 200, "step": 2, "sampling": null}}, {"class_name": "Int", "config": {"name": "units_4", "default": null, "conditions": [], "min_value": 1, "max_value": 200, "step": 2, "sampling": null}}, {"class_name": "Int", "config": {"name": "units_5", "default": null, "conditions": [], "min_value": 1, "max_value": 200, "step": 2, "sampling": null}}], "values": {"activation": "tanh", "first_units": 197, "num_layers": 3, "units_0": 31, "units_1": 117, "units_2": 121, "units_3": 159, "units_4": 59, "units_5": 143, "tuner/epochs": 34, "tuner/initial_epoch": 0, "tuner/bracket": 1, "tuner/round": 0}}, "metrics": {"metrics": {"loss": {"direction": "min", "observations": [{"value": [0.2810232639312744], "step": 25}]}, "accuracy": {"direction": "max", "observations": [{"value": [0.8957841396331787], "step": 25}]}, "val_loss": {"direction": "min", "observations": [{"value": [0.3055337369441986], "step": 25}]}, "val_accuracy": {"direction": "max", "observations": [{"value": [0.8947901129722595], "step": 25}]}}}, "score": 0.8947901129722595, "best_step": 25, "status": "COMPLETED"}